radicale_storage_etesync/__init__.py
radicale_storage_etesync/creds.py
radicale_storage_etesync-0.1.7.dist-info/METADATA
radicale_storage_etesync-0.1.7.dist-info/RECORD
radicale_storage_etesync-0.1.7.dist-info/WHEEL
radicale_storage_etesync-0.1.7.dist-info/top_level.txt
