Metadata-Version: 2.1
Name: radicale-storage-etesync
Version: 0.1.7
Summary: An EteSync storage plugin for Radicale
Home-page: https://github.com/etesync/radicale_storage_etesync
Author: EteSync
Author-email: development@etesync.com
License: GPL
Keywords: etesync,encryption,sync,pim,radicale
Platform: UNKNOWN
Requires-Dist: etesync (>=0.5.5)
Requires-Dist: Radicale (>=2.1.10)
